Metadata-Version: 2.4
Name: tts-webui.audiocraft
Version: 1.4.0a2
Summary: Audio generation research library for PyTorch
Home-page: https://github.com/facebookresearch/audiocraft
Author: FAIR Speech & Audio
Author-email: defossez@meta.com, jadecopet@meta.com
License: MIT License
Classifier: License :: OSI Approved :: MIT License
Classifier: Topic :: Multimedia :: Sound/Audio
Classifier: Topic :: Scientific/Engineering :: Artificial Intelligence
Requires-Python: >=3.8.0
License-File: LICENSE
License-File: LICENSE_weights
Requires-Dist: av>=11.0.0
Requires-Dist: einops
Requires-Dist: flashy>=0.0.1
Requires-Dist: hydra-core>=1.1
Requires-Dist: hydra_colorlog
Requires-Dist: julius
Requires-Dist: num2words
Requires-Dist: numpy<2.0.0
Requires-Dist: sentencepiece
Requires-Dist: spacy>=3.7.6
Requires-Dist: torch
Requires-Dist: torchaudio
Requires-Dist: huggingface_hub
Requires-Dist: tqdm
Requires-Dist: transformers>=4.31.0
Requires-Dist: xformers
Requires-Dist: demucs
Requires-Dist: librosa
Requires-Dist: soundfile
Requires-Dist: gradio
Requires-Dist: torchmetrics
Requires-Dist: encodec
Requires-Dist: protobuf
Requires-Dist: torchvision
Requires-Dist: torchtext
Requires-Dist: pesq
Requires-Dist: pystoi
Provides-Extra: dev
Requires-Dist: coverage; extra == "dev"
Requires-Dist: flake8; extra == "dev"
Requires-Dist: mypy; extra == "dev"
Requires-Dist: pdoc3; extra == "dev"
Requires-Dist: pytest; extra == "dev"
Provides-Extra: wm
Requires-Dist: audioseal; extra == "wm"
Dynamic: author
Dynamic: author-email
Dynamic: classifier
Dynamic: description
Dynamic: description-content-type
Dynamic: home-page
Dynamic: license
Dynamic: license-file
Dynamic: provides-extra
Dynamic: requires-dist
Dynamic: requires-python
Dynamic: summary
